tarot/__init__.py
tarot/tarot.py
tarot-0.0.4.dist-info/METADATA
tarot-0.0.4.dist-info/WHEEL
tarot-0.0.4.dist-info/top_level.txt
tarot-0.0.4.dist-info/RECORD
